<?xml version = '1.0' encoding = 'UTF-8'?>
<TableProxyOraclev12c class="oracle.dbtools.crest.model.design.storage.oracle.v12c.TableProxyOraclev12c" name="SECCHI_WATER_COLOUR_LOOKUP" directorySegmentName="seg_1" id="790BD130-CC18-1571-41A5-A1ACAAE22C69">
<createdBy>darbo</createdBy>
<createdTime>2024-02-13 17:12:15 UTC</createdTime>
<ownerDesignName>MEDS_DATA</ownerDesignName>
<schemaObject>198B7359-7E07-FB02-B07C-A0A91EE44FE7</schemaObject>
<logging>YES</logging>
<partitionedRowMovement>DISABLE</partitionedRowMovement>
<segment>D7B54673-F74D-BFE1-8C5D-FBA86950D400</segment>
<tableSpace>01F2BAC7-B949-43A6-09CC-CECB09A3E209</tableSpace>
<temporaryChanged>false</temporaryChanged>
<accessDriverType>oracle_loader</accessDriverType>
<rejectLimit></rejectLimit>
<inMemory>NO</inMemory>
<columnProxies itemClass="oracle.dbtools.crest.model.design.storage.oracle.v12c.ColumnProxyOraclev12c">
<ColumnProxy name="SECCHI_COLOUR_NAME" id="22589950-475B-0A17-83EB-BF4759506880">
<createdBy>darbo</createdBy>
<createdTime>2024-02-13 17:12:19 UTC</createdTime>
<ownerDesignName>MEDS_DATA</ownerDesignName>
<defaultValue>NULL</defaultValue>
</ColumnProxy>
<ColumnProxy name="SECCHI_COLOUR_H631A_SCALE" id="C96D8507-EBC8-C9DB-0A20-70CECFF14F75">
<createdBy>darbo</createdBy>
<createdTime>2024-02-13 17:12:19 UTC</createdTime>
<ownerDesignName>MEDS_DATA</ownerDesignName>
<defaultValue>NULL</defaultValue>
</ColumnProxy>
</columnProxies>
</TableProxyOraclev12c>