<?xml version = '1.0' encoding = 'UTF-8'?>
<TableProxyOraclev12c class="oracle.dbtools.crest.model.design.storage.oracle.v12c.TableProxyOraclev12c" name="REPRES_PROFILE_L2_NOV" directorySegmentName="seg_1" id="9B51B204-D9E0-675C-19E8-ED3D55BFB655">
<createdBy>d.arboittedossantos</createdBy>
<createdTime>2024-03-14 14:47:24 UTC</createdTime>
<ownerDesignName>MEDS_DATA</ownerDesignName>
<schemaObject>FD77D69E-489C-FEFD-81EE-34209F1C13AA</schemaObject>
<logging>YES</logging>
<partitionedRowMovement>DISABLE</partitionedRowMovement>
<segment>2A11820E-EDCF-FF28-336C-C7811EDF39B9</segment>
<tableSpace>EC0DC591-CC8E-BC50-EEE8-5A0B46384BB0</tableSpace>
<temporaryChanged>false</temporaryChanged>
<accessDriverType>oracle_loader</accessDriverType>
<rejectLimit></rejectLimit>
<inMemory>NO</inMemory>
<columnProxies itemClass="oracle.dbtools.crest.model.design.storage.oracle.v12c.ColumnProxyOraclev12c">
<ColumnProxy name="SIGMA_T" id="0DE55628-6A02-4036-9565-B8C3815EAC59">
<createdBy>d.arboittedossantos</createdBy>
<createdTime>2024-03-14 14:47:26 UTC</createdTime>
<ownerDesignName>MEDS_DATA</ownerDesignName>
</ColumnProxy>
<ColumnProxy name="GRID_INDEX" id="1BA8E4AA-22BB-BF8E-0A8F-3FA334581117">
<createdBy>d.arboittedossantos</createdBy>
<createdTime>2024-03-14 14:47:26 UTC</createdTime>
<ownerDesignName>MEDS_DATA</ownerDesignName>
</ColumnProxy>
<ColumnProxy name="RH_SALINITY" id="25BDC9C0-6DB3-6A54-B272-9320C8730E64">
<createdBy>d.arboittedossantos</createdBy>
<createdTime>2024-03-14 14:47:26 UTC</createdTime>
<ownerDesignName>MEDS_DATA</ownerDesignName>
</ColumnProxy>
<ColumnProxy name="LONGITUDE" id="266C6F0A-1476-3758-FF3E-FFFF47FD3C66">
<createdBy>d.arboittedossantos</createdBy>
<createdTime>2024-03-14 14:47:26 UTC</createdTime>
<ownerDesignName>MEDS_DATA</ownerDesignName>
</ColumnProxy>
<ColumnProxy name="LATITUDE" id="354506E2-B6EF-00B9-E0E4-239F6B955833">
<createdBy>d.arboittedossantos</createdBy>
<createdTime>2024-03-14 14:47:26 UTC</createdTime>
<ownerDesignName>MEDS_DATA</ownerDesignName>
</ColumnProxy>
<ColumnProxy name="LH_TEMPERATURE" id="6E4801B7-A009-429B-B509-748411A468C9">
<createdBy>d.arboittedossantos</createdBy>
<createdTime>2024-03-14 14:47:26 UTC</createdTime>
<ownerDesignName>MEDS_DATA</ownerDesignName>
</ColumnProxy>
<ColumnProxy name="LH_SOUND_SPEED" id="89FA643E-9F81-D2C1-1867-B76C3A0B2C05">
<createdBy>d.arboittedossantos</createdBy>
<createdTime>2024-03-14 14:47:26 UTC</createdTime>
<ownerDesignName>MEDS_DATA</ownerDesignName>
</ColumnProxy>
<ColumnProxy name="LH_SIGMA_T" id="9C84FB64-FC5C-2F40-99A7-74C1D830668B">
<createdBy>d.arboittedossantos</createdBy>
<createdTime>2024-03-14 14:47:26 UTC</createdTime>
<ownerDesignName>MEDS_DATA</ownerDesignName>
</ColumnProxy>
<ColumnProxy name="SALINITY" id="A08BE351-A793-3276-4B4F-C9C2B545BB55">
<createdBy>d.arboittedossantos</createdBy>
<createdTime>2024-03-14 14:47:26 UTC</createdTime>
<ownerDesignName>MEDS_DATA</ownerDesignName>
</ColumnProxy>
<ColumnProxy name="RH_TEMPERATURE" id="A1EE53D5-3E4F-859F-467A-962FF3920D80">
<createdBy>d.arboittedossantos</createdBy>
<createdTime>2024-03-14 14:47:26 UTC</createdTime>
<ownerDesignName>MEDS_DATA</ownerDesignName>
</ColumnProxy>
<ColumnProxy name="TEMPERATURE" id="AD91DE3B-6350-6335-5D60-82F4D61D5AFF">
<createdBy>d.arboittedossantos</createdBy>
<createdTime>2024-03-14 14:47:26 UTC</createdTime>
<ownerDesignName>MEDS_DATA</ownerDesignName>
</ColumnProxy>
<ColumnProxy name="DEPTH" id="AEB0BC18-96CC-E897-1ACA-08CA6B3201E8">
<createdBy>d.arboittedossantos</createdBy>
<createdTime>2024-03-14 14:47:26 UTC</createdTime>
<ownerDesignName>MEDS_DATA</ownerDesignName>
</ColumnProxy>
<ColumnProxy name="RH_SOUND_SPEED" id="B55C1EC8-D553-D1C0-33B3-3994DD44CE22">
<createdBy>d.arboittedossantos</createdBy>
<createdTime>2024-03-14 14:47:26 UTC</createdTime>
<ownerDesignName>MEDS_DATA</ownerDesignName>
</ColumnProxy>
<ColumnProxy name="DATATYPE" id="C50D4208-F3AC-9702-5618-B10E2C90492B">
<createdBy>d.arboittedossantos</createdBy>
<createdTime>2024-03-14 14:47:26 UTC</createdTime>
<ownerDesignName>MEDS_DATA</ownerDesignName>
<defaultValue>&apos;GENERIC&apos;</defaultValue>
</ColumnProxy>
<ColumnProxy name="SOUND_SPEED" id="D530428A-496F-BF83-078C-81DD58A13DC1">
<createdBy>d.arboittedossantos</createdBy>
<createdTime>2024-03-14 14:47:26 UTC</createdTime>
<ownerDesignName>MEDS_DATA</ownerDesignName>
</ColumnProxy>
<ColumnProxy name="RH_SIGMA_T" id="EDE1E882-9285-4B87-9929-A05E1465E0B7">
<createdBy>d.arboittedossantos</createdBy>
<createdTime>2024-03-14 14:47:26 UTC</createdTime>
<ownerDesignName>MEDS_DATA</ownerDesignName>
</ColumnProxy>
<ColumnProxy name="TEMP_STDEV" id="F29BB357-1B49-C850-8223-789C51A98D9B">
<createdBy>d.arboittedossantos</createdBy>
<createdTime>2024-03-14 14:47:26 UTC</createdTime>
<ownerDesignName>MEDS_DATA</ownerDesignName>
</ColumnProxy>
<ColumnProxy name="LH_SALINITY" id="F3742CD1-1434-265D-2E7E-EE9A3F8B45E1">
<createdBy>d.arboittedossantos</createdBy>
<createdTime>2024-03-14 14:47:26 UTC</createdTime>
<ownerDesignName>MEDS_DATA</ownerDesignName>
</ColumnProxy>
<ColumnProxy name="SALINITY_STDEV" id="F98BC43D-500A-1ED9-9BEA-653740C3923D">
<createdBy>d.arboittedossantos</createdBy>
<createdTime>2024-03-14 14:47:26 UTC</createdTime>
<ownerDesignName>MEDS_DATA</ownerDesignName>
</ColumnProxy>
</columnProxies>
<indexProxies>
<IndexProxy class="oracle.dbtools.crest.model.design.storage.oracle.v10g.IndexProxyOraclev10g" name="IDX_PROFILEL2NOV_LATLON" id="975F5739-D8C0-9BAD-C0B4-FEDC48AB997F">
<createdBy>d.arboittedossantos</createdBy>
<createdTime>2024-03-14 14:47:29 UTC</createdTime>
<ownerDesignName>MEDS_DATA</ownerDesignName>
<schemaObject>FD77D69E-489C-FEFD-81EE-34209F1C13AA</schemaObject>
<segment>85844A5E-DFDB-ACA5-F5A8-D7DFDBE60022</segment>
<tableSpace>EC0DC591-CC8E-BC50-EEE8-5A0B46384BB0</tableSpace>
</IndexProxy>
<IndexProxy class="oracle.dbtools.crest.model.design.storage.oracle.v10g.IndexProxyOraclev10g" name="IDX_REPPROFILEL2_NOV" id="B0F93B49-20D1-A738-B272-E4C15D1EB2A9">
<createdBy>d.arboittedossantos</createdBy>
<createdTime>2024-03-14 14:47:29 UTC</createdTime>
<ownerDesignName>MEDS_DATA</ownerDesignName>
<schemaObject>FD77D69E-489C-FEFD-81EE-34209F1C13AA</schemaObject>
<segment>85844A5E-DFDB-ACA5-F5A8-D7DFDBE60022</segment>
<tableSpace>EC0DC591-CC8E-BC50-EEE8-5A0B46384BB0</tableSpace>
</IndexProxy>
</indexProxies>
</TableProxyOraclev12c>