<?xml version = '1.0' encoding = 'UTF-8'?>
<TableProxyOraclev12c class="oracle.dbtools.crest.model.design.storage.oracle.v12c.TableProxyOraclev12c" name="UNIFIED_SECCHI_OBSERVATION" directorySegmentName="seg_1" id="9E14F557-FB4C-C878-7F3F-81AB6F79A471">
<createdBy>d.arboittedossantos</createdBy>
<createdTime>2024-03-14 14:47:24 UTC</createdTime>
<ownerDesignName>MEDS_DATA</ownerDesignName>
<schemaObject>FD77D69E-489C-FEFD-81EE-34209F1C13AA</schemaObject>
<logging>YES</logging>
<partitionedRowMovement>DISABLE</partitionedRowMovement>
<segment>2A11820E-EDCF-FF28-336C-C7811EDF39B9</segment>
<tableSpace>EC0DC591-CC8E-BC50-EEE8-5A0B46384BB0</tableSpace>
<temporaryChanged>false</temporaryChanged>
<accessDriverType>oracle_loader</accessDriverType>
<rejectLimit></rejectLimit>
<inMemory>NO</inMemory>
<columnProxies itemClass="oracle.dbtools.crest.model.design.storage.oracle.v12c.ColumnProxyOraclev12c">
<ColumnProxy name="LATITUDE" id="222E2118-3F9B-BA6C-EE8E-1A75F21F14EA">
<createdBy>d.arboittedossantos</createdBy>
<createdTime>2024-03-14 14:47:26 UTC</createdTime>
<ownerDesignName>MEDS_DATA</ownerDesignName>
</ColumnProxy>
<ColumnProxy name="DATE_RECORDED" id="2260FA92-9E25-2604-5009-751638E27EF9">
<createdBy>d.arboittedossantos</createdBy>
<createdTime>2024-03-14 14:47:26 UTC</createdTime>
<ownerDesignName>MEDS_DATA</ownerDesignName>
</ColumnProxy>
<ColumnProxy name="LOCATION" id="81E16AB5-8B1A-A5E1-5D0B-F3871CD35264">
<createdBy>d.arboittedossantos</createdBy>
<createdTime>2024-03-14 14:47:26 UTC</createdTime>
<ownerDesignName>MEDS_DATA</ownerDesignName>
</ColumnProxy>
<ColumnProxy name="MEDS_JOB_NUMBER" id="C92FADB1-B20E-DF59-9656-B472194C62EE">
<createdBy>d.arboittedossantos</createdBy>
<createdTime>2024-03-14 14:47:26 UTC</createdTime>
<ownerDesignName>MEDS_DATA</ownerDesignName>
</ColumnProxy>
<ColumnProxy name="SRC" id="CEB61B6B-2002-9E48-BB19-2DA68AB5364E">
<createdBy>d.arboittedossantos</createdBy>
<createdTime>2024-03-14 14:47:26 UTC</createdTime>
<ownerDesignName>MEDS_DATA</ownerDesignName>
</ColumnProxy>
<ColumnProxy name="LONGITUDE" id="DC91690D-7758-BD29-A28F-2382A924155A">
<createdBy>d.arboittedossantos</createdBy>
<createdTime>2024-03-14 14:47:26 UTC</createdTime>
<ownerDesignName>MEDS_DATA</ownerDesignName>
</ColumnProxy>
<ColumnProxy name="MEDS_OBSERVATION_NUMBER" id="ED567C1F-CDBE-B680-010A-AF284E47DB7B">
<createdBy>d.arboittedossantos</createdBy>
<createdTime>2024-03-14 14:47:26 UTC</createdTime>
<ownerDesignName>MEDS_DATA</ownerDesignName>
</ColumnProxy>
</columnProxies>
<indexProxies>
<IndexProxy class="oracle.dbtools.crest.model.design.storage.oracle.v10g.IndexProxyOraclev10g" name="IDX_UNIFIED_SECCI_OBS" id="307F7603-A057-DE24-566F-15D6FDE30676">
<createdBy>d.arboittedossantos</createdBy>
<createdTime>2024-03-14 14:47:30 UTC</createdTime>
<ownerDesignName>MEDS_DATA</ownerDesignName>
<schemaObject>FD77D69E-489C-FEFD-81EE-34209F1C13AA</schemaObject>
<segment>85844A5E-DFDB-ACA5-F5A8-D7DFDBE60022</segment>
<tableSpace>EC0DC591-CC8E-BC50-EEE8-5A0B46384BB0</tableSpace>
</IndexProxy>
<IndexProxy class="oracle.dbtools.crest.model.design.storage.oracle.v10g.IndexProxyOraclev10g" name="IDX_UNIFIED_SECCHI_LATLON" id="6833B951-FCAC-6998-C68F-ED6AE9F2B4E2">
<createdBy>d.arboittedossantos</createdBy>
<createdTime>2024-03-14 14:47:30 UTC</createdTime>
<ownerDesignName>MEDS_DATA</ownerDesignName>
<schemaObject>FD77D69E-489C-FEFD-81EE-34209F1C13AA</schemaObject>
<segment>85844A5E-DFDB-ACA5-F5A8-D7DFDBE60022</segment>
<tableSpace>EC0DC591-CC8E-BC50-EEE8-5A0B46384BB0</tableSpace>
</IndexProxy>
<IndexProxy class="oracle.dbtools.crest.model.design.storage.oracle.v10g.IndexProxyOraclev10g" name="SI_UNIFIEDSECCHI" id="88AAE159-FDC2-0474-BBB8-4CD7C56677D1">
<createdBy>d.arboittedossantos</createdBy>
<createdTime>2024-03-14 14:47:30 UTC</createdTime>
<ownerDesignName>MEDS_DATA</ownerDesignName>
<schemaObject>FD77D69E-489C-FEFD-81EE-34209F1C13AA</schemaObject>
<indexDomainParameters>SDO_LEVEL=2 SDO_NUMTILES=1 TABLESPACE = INDX </indexDomainParameters>
<indexType>MDSYS.SPATIAL_INDEX_V2</indexType>
<segment>88419D06-90CC-D9E4-BCD3-BE3E615FF383</segment>
<tableSpace>EC0DC591-CC8E-BC50-EEE8-5A0B46384BB0</tableSpace>
</IndexProxy>
</indexProxies>
</TableProxyOraclev12c>