<?xml version = '1.0' encoding = 'UTF-8'?>
<SequenceOraclev10g class="oracle.dbtools.crest.model.design.storage.oracle.v10g.SequenceOraclev10g" name="R138" directorySegmentName="seg_1" id="00A73E6E-00A8-D4A4-51E0-4A0D5FB8FD64">
<sourceConnName>MEDS</sourceConnName>
<sourceObjSchema>MEDSDATA</sourceObjSchema>
<sourceObjName>R138</sourceObjName>
<createdBy>darbo</createdBy>
<createdTime>2024-02-13 17:12:07 UTC</createdTime>
<ownerDesignName>MEDS</ownerDesignName>
<cache>20</cache>
<incrementBy>16</incrementBy>
<maxValue>2147483647</maxValue>
<minValue>1</minValue>
<user>EC810D67-49CA-B5C0-3EC6-B779C0C6D3EC</user>
</SequenceOraclev10g>
