<?xml version = '1.0' encoding = 'UTF-8'?>
<TableProxyOraclev12c class="oracle.dbtools.crest.model.design.storage.oracle.v12c.TableProxyOraclev12c" name="WVS_3M" directorySegmentName="seg_2" id="9063F811-4A1D-EA2C-F270-425F9042A02E">
<createdBy>darbo</createdBy>
<createdTime>2024-02-13 17:12:16 UTC</createdTime>
<ownerDesignName>MEDS</ownerDesignName>
<schemaObject>198B7359-7E07-FB02-B07C-A0A91EE44FE7</schemaObject>
<logging>YES</logging>
<partitionedRowMovement>DISABLE</partitionedRowMovement>
<segment>D7B54673-F74D-BFE1-8C5D-FBA86950D400</segment>
<tableSpace>01F2BAC7-B949-43A6-09CC-CECB09A3E209</tableSpace>
<temporaryChanged>false</temporaryChanged>
<accessDriverType>oracle_loader</accessDriverType>
<rejectLimit></rejectLimit>
<inMemory>NO</inMemory>
<columnProxies itemClass="oracle.dbtools.crest.model.design.storage.oracle.v12c.ColumnProxyOraclev12c">
<ColumnProxy name="SE_ANNO_CAD_DATA" id="0106934E-4D8E-202B-FBC2-1C1DD85CBEB6">
<createdBy>darbo</createdBy>
<createdTime>2024-02-13 17:12:19 UTC</createdTime>
<ownerDesignName>MEDS</ownerDesignName>
</ColumnProxy>
<ColumnProxy name="ID" id="121AB170-204C-8169-75BB-6915A5FC8DCB">
<createdBy>darbo</createdBy>
<createdTime>2024-02-13 17:12:19 UTC</createdTime>
<ownerDesignName>MEDS</ownerDesignName>
</ColumnProxy>
<ColumnProxy name="CVL" id="296DAEA0-E264-04A3-291C-AC71FDDB2D09">
<createdBy>darbo</createdBy>
<createdTime>2024-02-13 17:12:19 UTC</createdTime>
<ownerDesignName>MEDS</ownerDesignName>
</ColumnProxy>
<ColumnProxy name="FAC_ID" id="5B416E3B-9106-8241-C68F-42A25682FAE5">
<createdBy>darbo</createdBy>
<createdTime>2024-02-13 17:12:19 UTC</createdTime>
<ownerDesignName>MEDS</ownerDesignName>
</ColumnProxy>
<ColumnProxy name="CVH" id="AE744B25-8BF5-FB63-A1B1-C46E55DB00AD">
<createdBy>darbo</createdBy>
<createdTime>2024-02-13 17:12:19 UTC</createdTime>
<ownerDesignName>MEDS</ownerDesignName>
</ColumnProxy>
<ColumnProxy name="SHAPE" id="B02D0A5D-123B-503B-6A75-62D343BFD286">
<createdBy>darbo</createdBy>
<createdTime>2024-02-13 17:12:19 UTC</createdTime>
<ownerDesignName>MEDS</ownerDesignName>
</ColumnProxy>
<ColumnProxy name="FACC" id="BC0C22F3-8DD7-90D3-45D1-1CA899EB0F48">
<createdBy>darbo</createdBy>
<createdTime>2024-02-13 17:12:19 UTC</createdTime>
<ownerDesignName>MEDS</ownerDesignName>
</ColumnProxy>
<ColumnProxy name="FACC_DESCR" id="CC7A7B1C-F60D-E5C0-F63C-05156FE7C70F">
<createdBy>darbo</createdBy>
<createdTime>2024-02-13 17:12:19 UTC</createdTime>
<ownerDesignName>MEDS</ownerDesignName>
</ColumnProxy>
<ColumnProxy name="TILE_ID" id="E4A3DB87-6E86-58C7-1EF8-9E7EA82C833D">
<createdBy>darbo</createdBy>
<createdTime>2024-02-13 17:12:19 UTC</createdTime>
<ownerDesignName>MEDS</ownerDesignName>
</ColumnProxy>
<ColumnProxy name="OBJECTID" id="FCF52120-8544-18CF-02D4-C692516094F2">
<createdBy>darbo</createdBy>
<createdTime>2024-02-13 17:12:19 UTC</createdTime>
<ownerDesignName>MEDS</ownerDesignName>
</ColumnProxy>
</columnProxies>
<indexProxies>
<IndexProxy class="oracle.dbtools.crest.model.design.storage.oracle.v10g.IndexProxyOraclev10g" name="SI_BATHY" id="C9ECFC6B-D6E9-0F60-CC2F-F247189B23F8">
<createdBy>darbo</createdBy>
<createdTime>2024-02-13 17:12:28 UTC</createdTime>
<ownerDesignName>MEDS</ownerDesignName>
<schemaObject>198B7359-7E07-FB02-B07C-A0A91EE44FE7</schemaObject>
<segment>9C9FB71F-25FA-579F-2DAE-FC1B89628461</segment>
<tableSpace>01F2BAC7-B949-43A6-09CC-CECB09A3E209</tableSpace>
</IndexProxy>
<IndexProxy class="oracle.dbtools.crest.model.design.storage.oracle.v10g.IndexProxyOraclev10g" name="BATHY_CVL" id="EC17AC8C-2D54-6B0A-E1F1-F593A38A1F3E">
<createdBy>darbo</createdBy>
<createdTime>2024-02-13 17:12:28 UTC</createdTime>
<ownerDesignName>MEDS</ownerDesignName>
<schemaObject>198B7359-7E07-FB02-B07C-A0A91EE44FE7</schemaObject>
<segment>04DA2C71-86F8-F75A-7467-947016074CAA</segment>
<tableSpace>01F2BAC7-B949-43A6-09CC-CECB09A3E209</tableSpace>
</IndexProxy>
</indexProxies>
<lobStorages>
<LobStorage class="oracle.dbtools.crest.model.design.storage.oracle.v11g.LobStorageOraclev11g" name="SYS_LOB0000478729C00017$$" id="22EAB1CA-41CF-5E89-066C-7AD4D32B23D0">
<createdBy>darbo</createdBy>
<createdTime>2024-02-13 17:12:36 UTC</createdTime>
<ownerDesignName>MEDS</ownerDesignName>
<cache>NOCACHE</cache>
<chunk>8192</chunk>
<column>SE_ANNO_CAD_DATA</column>
<compression>NO</compression>
<duplication>KEEP_DUPLICATES</duplication>
<logging>YES</logging>
<tableSpace>01F2BAC7-B949-43A6-09CC-CECB09A3E209</tableSpace>
<lobStorageType>SECUREFILE</lobStorageType>
</LobStorage>
</lobStorages>
</TableProxyOraclev12c>
